PyBNG/PyBNG.py
PyBNG/PyBNGError.py
PyBNG/__init__.py
example/PyBNG.py
example/PyBNGError.py
example/__init__.py
example/example.py
pybng-0.2.0.dist-info/METADATA
pybng-0.2.0.dist-info/WHEEL
pybng-0.2.0.dist-info/top_level.txt
pybng-0.2.0.dist-info/RECORD
