Metadata-Version: 2.4
Name: PyBNG
Version: 0.2.0
Summary: A library to convert BNG/OSNG coordinates 
Home-page: https://github.com/ThunderStruct/PyBNG
Author: Mohamed Shahawy
Author-email: envious-citizen.0s@icloud.com
Keywords: gis mapping coordinates grid-reference mapping ordiance-survey lat-long bng all-numeric
Classifier: Intended Audience :: Developers
Classifier: Intended Audience :: Science/Research
Classifier: Intended Audience :: Other Audience
Classifier: Topic :: Education
Classifier: Topic :: Internet :: WWW/HTTP :: WSGI :: Application
Classifier: Topic :: Scientific/Engineering :: GIS
Classifier: Topic :: Utilities
Classifier: License :: OSI Approved :: MIT License
Classifier: Programming Language :: Python :: 3.4
Classifier: Programming Language :: Python :: 3.5
Classifier: Operating System :: MacOS
Classifier: Operating System :: Microsoft :: Windows
Classifier: Operating System :: POSIX :: Linux
Requires-Python: >=3.6
Requires-Dist: OSGridConverter
Dynamic: author
Dynamic: author-email
Dynamic: classifier
Dynamic: description
Dynamic: description-content-type
Dynamic: home-page
Dynamic: keywords
Dynamic: requires-dist
Dynamic: requires-python
Dynamic: summary
